[{"bairro":"CAJU","cargo_representante":"Diretor Gerente","cep":"20931675","cidade":"Rio de Janeiro","cnpj":92693118000160,"complemento":"SALAS 801, 901, 1001, 1101, 1201, 1301, ","data_registro_ans":"16/12/1998","ddd":"21","email":"flavio.bitter@bradescoseguros.com.br","fax":"25031329","logradouro":"AVENIDA RIO DE JANEIRO","modalidade":"Seguradora Especializada em Sa\u00fade","nome_fantasia":"BRADESCO SAUDE S.A.","numero":"555","razao_social":"BRADESCO SA\u00daDE S.A.","registro_ans":5711,"representante":"FLAVIO BITTER ","telefone":"31666000","uf":"RJ"},{"bairro":"DEZOITO DO FORTE EMPRESARIAL/A","cargo_representante":"Diretor Gerente","cep":"06472900","cidade":"Barueri","cnpj":15011651000154,"complemento":"17\u00ba ANDAR, SALA 1701-PARTE","data_registro_ans":"29/04/2019","ddd":"21","email":"flavio.bitter@bradescoseguros.com.br","fax":"25031329","logradouro":"AVENIDA ALPHAVILLE","modalidade":"Medicina de Grupo","nome_fantasia":"","numero":"779","razao_social":"BRADESCO SA\u00daDE - OPERADORA DE PLANOS  S/A","registro_ans":421715,"representante":"FL\u00c1VIO BITTER","telefone":"25031076","uf":"SP"}]